<?xml version="1.0" encoding="iso-8859-1" ?>
<newsitem itemid="86276" id="root" date="1996-09-30" xml:lang="en">
<title>FRANCE: Ford expects Europe small car market to grow.</title>
<headline>Ford expects Europe small car market to grow.</headline>
<dateline>PARIS 1996-09-30</dateline>
<text>
<p>Ford Motor Co chairman Alex Trotman said on Monday he expected the small car market in Europe to grow to 4.5 million units by the year 2000 from 3.85 million currently.</p>
<p>Trotman, in Paris to introduce Ford's Ka minicar, told reporters the share of the small car market was expected to grow to 35 percent of Europe's total car market by the year 2000 from 32 percent.</p>
<p>-- Paris Newsroom, +33 1 4221 5452</p>
</text>
<copyright>(c) Reuters Limited 1996</copyright>
<metadata>
<codes class="bip:countries:1.0">
  <code code="FRA">
    <editdetail attribution="Reuters BIP Coding Group" action="confirmed" date="1996-09-30"/>
  </code>
</codes>
<codes class="bip:industries:1.0">
  <code code="I35101">
    <editdetail attribution="Reuters BIP Coding Group" action="confirmed" date="1996-09-30"/>
  </code>
</codes>
<codes class="bip:topics:1.0">
  <code code="C31">
    <editdetail attribution="Reuters BIP Coding Group" action="confirmed" date="1996-09-30"/>
  </code>
  <code code="CCAT">
    <editdetail attribution="Reuters BIP Coding Group" action="confirmed" date="1996-09-30"/>
  </code>
</codes>
<dc element="dc.date.created" value="1996-09-30"/>
<dc element="dc.publisher" value="Reuters Holdings Plc"/>
<dc element="dc.date.published" value="1996-09-30"/>
<dc element="dc.source" value="Reuters"/>
<dc element="dc.creator.location" value="PARIS"/>
<dc element="dc.creator.location.country.name" value="FRANCE"/>
<dc element="dc.source" value="Reuters"/>
</metadata>
</newsitem>
